foxlator/__init__.py
foxlator/__main__.py
foxlator/foxlator.py
foxlator/sub_movie_generator.py
foxlator/utils/checks.py
foxlator/utils/system.py
foxlator-0.11.0.dist-info/METADATA
foxlator-0.11.0.dist-info/WHEEL
foxlator-0.11.0.dist-info/entry_points.txt
foxlator-0.11.0.dist-info/RECORD
